{
	"list": [
		{
			"category": "Family",
			"icon": "fa-solid fa-user",
			"images": [
				{ "img": "/faces/gianni.png", "alt": "Gianni" },
				{ "img": "/faces/imogene.png", "alt": "Imogene" },
				{ "img": "/faces/emily.jpg", "alt": "Mom" },
				{ "img": "/faces/mark.png", "alt": "Dad" },
				{ "img": "/faces/kangaroo.png", "alt": "Kangaroo" },
				{ "img": "/faces/walter.png", "alt": "Walter" }
			]
		},
		{
			"category": "Dinosaurs",
			"icon": "fa-solid fa-dragon",
			"images": [
				{ "img": "/dinosaurs/raptor_green.jpg", "alt": "raptor" },
				{ "img": "/dinosaurs/parasaur_purple.jpg", "alt": "parasaur" },
				{ "img": "/dinosaurs/spino_yellow.jpg", "alt": "spino" },
				{ "img": "/dinosaurs/stego_red.jpg", "alt": "stego" },
				{ "img": "/dinosaurs/trex_teal.jpg", "alt": "t-rex" },
				{ "img": "/dinosaurs/ptero_pink.jpg", "alt": "ptero" }
			]
		},
		{
			"category": "Eggs",
			"icon": "fa-solid fa-egg",
			"images": [
				{ "img": "/dinoEggs/egg1.jpg", "alt": "EGG" },
				{ "img": "/dinoEggs/egg2.jpg", "alt": "EGG" },
				{ "img": "/dinoEggs/egg3.jpg", "alt": "EGG" },
				{ "img": "/dinoEggs/egg4.jpg", "alt": "EGG" },
				{ "img": "/dinoEggs/egg5.jpg", "alt": "EGG" },
				{ "img": "/dinoEggs/egg6.jpg", "alt": "EGG" }
			]
		}
	]
}
